poetry_demo/__init__.py
poetry_demo/build/main/Analysis-00.toc
poetry_demo/build/main/EXE-00.toc
poetry_demo/build/main/PKG-00.toc
poetry_demo/build/main/PYZ-00.pyz
poetry_demo/build/main/PYZ-00.toc
poetry_demo/build/main/base_library.zip
poetry_demo/build/main/main.pkg
poetry_demo/build/main/warn-main.txt
poetry_demo/build/main/xref-main.html
poetry_demo/dist/main
poetry_demo/main.py
poetry_demo/main.spec
poetry_demo/operation_object/__init__.py
poetry_demo/operation_object/eyetracking/__init__.py
poetry_demo/operation_object/eyetracking/eyetracking.py
poetry_demo/operation_object/message_sender/__init__.py
poetry_demo/operation_object/message_sender/message_sender.py
poetry_demo/operation_object/message_sender/metadata.toml
aroma_automation_test1289-0.1.0.dist-info/METADATA
aroma_automation_test1289-0.1.0.dist-info/WHEEL
aroma_automation_test1289-0.1.0.dist-info/RECORD
